reqsit/__init__.py
reqsit/main.py
reqsit-0.28.0.dist-info/METADATA
reqsit-0.28.0.dist-info/WHEEL
reqsit-0.28.0.dist-info/entry_points.txt
reqsit-0.28.0.dist-info/RECORD