Metadata-Version: 2.1
Name: reqsit
Version: 0.28.0
Summary: A CLI tool for converting requirements.txt entries to a form accepted by pyproject.toml.
License: MIT
Author: matt witt
Author-email: matt@wittsoft.xyz
Keywords: packaging,wheel
Classifier: Programming Language :: Python :: 3
Home-Page: https://github.com/dholth/enscons
Requires-Dist: scons>=3.0.5
Requires-Dist: pytoml>=0.1
Requires-Dist: setuptools
Requires-Dist: wheel
Requires-Dist: attrs
Requires-Dist: packaging>=20.9
Requires-Dist: editables==0.2; python_version > "3.0"
Requires-Dist: art==5.3
Requires-Dist: enscons==0.28.0
Requires-Dist: fire==0.4.0
Requires-Dist: pytest==6.2.5
Requires-Dist: pytest_mock==3.6.1
